script/__init__.py
script/zeptron.py
zeptron-1.0.6.dist-info/LICENSE
zeptron-1.0.6.dist-info/METADATA
zeptron-1.0.6.dist-info/WHEEL
zeptron-1.0.6.dist-info/entry_points.txt
zeptron-1.0.6.dist-info/requirements.txt
zeptron-1.0.6.dist-info/top_level.txt
zeptron-1.0.6.dist-info/RECORD
