Metadata-Version: 2.1
Name: zeptron
Version: 1.0.6
Summary: A super lightweight streaming module using ZMQ
Home-page: https://github.com/zeptron/zeptron
Author: Jose Mathias
Author-email: hello@zeptron.co
License: UNKNOWN
Platform: UNKNOWN
Classifier: Programming Language :: Python :: 3
Classifier: License :: OSI Approved :: MIT License
Classifier: Operating System :: OS Independent
Requires-Python: >=3.6
Requires-Dist: imagezmq (==1.1.1)
Requires-Dist: imutils (==0.5.3)
Requires-Dist: numpy (==1.19.0)
Requires-Dist: opencv-python (==4.1.1.26)
Requires-Dist: pyzmq (==19.0.1)
